<?xml version='1.0' encoding='utf-8'?><fdo_objects><document url="" di="0" bi="-1" date="2016-05-15"><facts><Address FactID="0" LeadID="0" FieldsInfo="n0;" pos="79" len="16" sn="1" fw="0" lw="3"><StreetName val="ГДЕ : КЛУБ 'ATLAS"/></Address><Date FactID="1" LeadID="1" FieldsInfo="n0;n1;" pos="1142" len="18" sn="12" fw="0" lw="3"><Data val="29 СЕНТЯБРЯ"/><prey val="КОГДА :"/></Date></facts><Leads><Lead text="&lt;l&gt;&lt;h t=&quot;ya&quot; di=&quot;0&quot; u=&quot;&quot;&gt;&lt;d&gt;2016-05-15 15:37&lt;/d&gt;&lt;s&gt;file&lt;/s&gt;&lt;/h&gt;&lt;b&gt;&lt;s&gt;&lt;S n0=&quot;&quot; lemma=&quot;где : клуб 'Atlas&quot;&gt;Где: клуб 'Atlas&lt;/S&gt;&lt;/s&gt;&lt;/b&gt;&lt;/l&gt;" id="0"/><Lead text="&lt;l&gt;&lt;h t=&quot;ya&quot; di=&quot;0&quot; u=&quot;&quot;&gt;&lt;d&gt;2016-05-15 15:37&lt;/d&gt;&lt;s&gt;file&lt;/s&gt;&lt;/h&gt;&lt;b&gt;&lt;s&gt;&lt;p n1=&quot;&quot; lemma=&quot;когда :&quot;&gt;Когда:&lt;/p&gt; &lt;D n0=&quot;&quot; lemma=&quot;29 сентября&quot;&gt;29 сентября&lt;/D&gt; в 19:00 Билеты от 350 грн&lt;/s&gt;&lt;/b&gt;&lt;/l&gt;" id="1"/></Leads></document>
</fdo_objects>