<?xml version='1.0' encoding='utf-8'?><fdo_objects><document url="" di="0" bi="-1" date="2016-05-15"><facts><Address FactID="0" LeadID="0" FieldsInfo="n0;" pos="75" len="18" sn="0" fw="11" lw="14"><StreetName val="ГДЕ : ВЕРБИЦКОГО 32"/></Address><Date FactID="1" LeadID="1" FieldsInfo="n0;n1;" pos="1130" len="30" sn="10" fw="8" lw="14"><Data val="СЕГОДНЯ , НАЧАЛО В 23:00"/><prey val="КОГДА :"/></Date></facts><Leads><Lead text="&lt;l&gt;&lt;h t=&quot;ya&quot; di=&quot;0&quot; u=&quot;&quot;&gt;&lt;d&gt;2016-05-15 13:21&lt;/d&gt;&lt;s&gt;file&lt;/s&gt;&lt;/h&gt;&lt;b&gt;&lt;s&gt;[ club87572674 | Пятница транадцатое в баре &quot;Black Rabbit&quot; ] ________________ &lt;S n0=&quot;&quot; lemma=&quot;Где : Вербицкого 32&quot;&gt;Где: Вербицкого 32&lt;/S&gt; Для многих обитателей земного шара пятница тринадцатое считается неудачным днем, когда все валится из рук и идет наперекосяк.&lt;/s&gt;&lt;/b&gt;&lt;/l&gt;" id="0"/><Lead text="&lt;l&gt;&lt;h t=&quot;ya&quot; di=&quot;0&quot; u=&quot;&quot;&gt;&lt;d&gt;2016-05-15 13:21&lt;/d&gt;&lt;s&gt;file&lt;/s&gt;&lt;/h&gt;&lt;b&gt;&lt;s&gt;Бронь: + 38 ( 073 ) 044-30-45 &lt;p n1=&quot;&quot; lemma=&quot;Когда :&quot;&gt;Когда:&lt;/p&gt; &lt;D n0=&quot;&quot; lemma=&quot;сегодня , начало в 23:00&quot;&gt;сегодня, начало в 23:00&lt;/D&gt;&lt;/s&gt;&lt;/b&gt;&lt;/l&gt;" id="1"/></Leads></document>
</fdo_objects>